{
  "labels": [
    {
      "index": 54,
      "label": "Sky",
      "confidence": 0.9047758
    },
    {
      "index": 408,
      "label": "Prairie",
      "confidence": 0.8237172
    },
    {
      "index": 359,
      "label": "Field",
      "confidence": 0.75818115
    },
    {
      "index": 366,
      "label": "Building",
      "confidence": 0.75064063
    },
    {
      "index": 266,
      "label": "Plant",
      "confidence": 0.7307705
    },
    {
      "index": 193,
      "label": "Forest",
      "confidence": 0.7209104
    },
    {
      "index": 337,
      "label": "Mountain",
      "confidence": 0.7091291
    },
    {
      "index": 114,
      "label": "Jungle",
      "confidence": 0.689201
    }
  ],
  "mlkitLabels": [
    {
      "index": 54,
      "label": "Sky",
      "confidence": 0.9047758
    },
    {
      "index": 408,
      "label": "Prairie",
      "confidence": 0.8237172
    },
    {
      "index": 359,
      "label": "Field",
      "confidence": 0.75818115
    },
    {
      "index": 366,
      "label": "Building",
      "confidence": 0.75064063
    },
    {
      "index": 266,
      "label": "Plant",
      "confidence": 0.7307705
    },
    {
      "index": 193,
      "label": "Forest",
      "confidence": 0.7209104
    },
    {
      "index": 337,
      "label": "Mountain",
      "confidence": 0.7091291
    },
    {
      "index": 114,
      "label": "Jungle",
      "confidence": 0.689201
    }
  ],
  "tags": [
    "phone_sample",
    "ishigaki"
  ],
  "mlkit": {
    "provider": "ML Kit",
    "generatedAt": "2026-06-29T06:40:51.522Z",
    "sourceImage": "25131-ishigaki/IMG_20260606_000327397.jpg",
    "command": "node rating_tool/scripts/mlkit-labeler-adb.mjs"
  }
}
